MANIFEST.in
README.rst
setup.py
getlyrics/__init__.py
getlyrics/__main__.py
getlyrics/getlyrics.py
getlyrics.egg-info/PKG-INFO
getlyrics.egg-info/SOURCES.txt
getlyrics.egg-info/dependency_links.txt
getlyrics.egg-info/entry_points.txt
getlyrics.egg-info/requires.txt
getlyrics.egg-info/top_level.txt