Metadata-Version: 1.1
Name: getlyrics
Version: 2.1.2
Summary: A Python program which gets the lyrics for a song and outputs them to stdout
Home-page: https://blha303.github.io/getlyrics/
Author: Steven Smith
Author-email: stevensmith.ome@gmail.com
License: MIT
Platform: UNKNOWN
Classifier: Development Status :: 4 - Beta
Classifier: License :: OSI Approved :: MIT License
Classifier: Programming Language :: Python :: 2.7
Classifier: Programming Language :: Python :: 2
Classifier: Programming Language :: Python :: 3.4
Classifier: Programming Language :: Python :: 3
Classifier: Intended Audience :: End Users/Desktop
Classifier: Intended Audience :: System Administrators
Classifier: Topic :: Multimedia :: Sound/Audio
